precompose/__init__.py
precompose/capture.py
precompose/main.py
precompose/pack.py
precompose-0.4.0.dist-info/LICENSE.md
precompose-0.4.0.dist-info/METADATA
precompose-0.4.0.dist-info/WHEEL
precompose-0.4.0.dist-info/entry_points.txt
precompose-0.4.0.dist-info/top_level.txt
precompose-0.4.0.dist-info/RECORD
