Metadata-Version: 2.1
Name: precompose
Version: 0.4.0
Summary: Import a Docker Compose application into ostree
Home-page: https://github.com/hello-seam/precompose
Author: Jordan Webb
Author-email: jordan@getseam.com
License: AGPL-3.0-or-later
Project-URL: Bug Tracker, https://github.com/hello-seam/precompose/issues
Project-URL: Source Code, https://github.com/hello-seam/precompose
Keywords: linux,docker,docker-compose,containers,ostree
Platform: UNKNOWN
Classifier: Development Status :: 4 - Beta
Classifier: Intended Audience :: Developers
Classifier: License :: OSI Approved :: GNU Affero General Public License v3 or later (AGPLv3+)
Classifier: Programming Language :: Python
Classifier: Programming Language :: Python :: 3 :: Only
Classifier: Programming Language :: Python :: 3.6
Classifier: Programming Language :: Python :: 3.7
Classifier: Programming Language :: Python :: 3.8
Classifier: Programming Language :: Python :: 3.9
Classifier: Operating System :: POSIX :: Linux
Requires-Python: >=3.6
License-File: LICENSE.md
Requires-Dist: ruamel.yaml
